sublimpy/__init__.py
sublimpy/gradients.py
sublimpy/tidy.py
sublimpy/utils.py
sublimpy/variables.py
sublimpy-0.0.1.dist-info/METADATA
sublimpy-0.0.1.dist-info/WHEEL
sublimpy-0.0.1.dist-info/top_level.txt
sublimpy-0.0.1.dist-info/RECORD
