Metadata-Version: 2.1
Name: sublimpy
Version: 0.0.1
Summary: Tools for working with data from the Sublimation of Snow project.
Home-page: https://github.com/elischwat/sublimpy
Author: Eli Schwat
Classifier: Programming Language :: Python :: 3
Classifier: License :: OSI Approved :: MIT License
Classifier: Operating System :: OS Independent
Requires-Python: >=3.11
